serialized_redis/__init__.py
serialized_redis_interface-0.3.1.dist-info/LICENSE
serialized_redis_interface-0.3.1.dist-info/METADATA
serialized_redis_interface-0.3.1.dist-info/WHEEL
serialized_redis_interface-0.3.1.dist-info/top_level.txt
serialized_redis_interface-0.3.1.dist-info/RECORD
