Metadata-Version: 2.1
Name: serialized-redis-interface
Version: 0.3.1
Summary: Redis python interface that serializes all values using json, pickle, msgpack or a custom serializer.
Home-page: https://github.com/michael-mri/serialized-redis
Author: Michael Rigoni
Author-email: michael.rigoni@gmail.com
Maintainer: Michael Rigoni
Maintainer-email: michael.rigoni@gmail.com
License: MIT
Keywords: Redis,key-value store,json,pickle,msgpack
Platform: UNKNOWN
Classifier: Development Status :: 4 - Beta
Classifier: Environment :: Console
Classifier: Intended Audience :: Developers
Classifier: License :: OSI Approved :: MIT License
Classifier: Operating System :: OS Independent
Classifier: Programming Language :: Python
Classifier: Programming Language :: Python :: 3
Classifier: Programming Language :: Python :: 3.5
Classifier: Programming Language :: Python :: 3.6
Classifier: Programming Language :: Python :: 3.7
Requires-Python: >=3
Provides-Extra: msgpack
